DatasetGeneratorAI/__init__.py
DatasetGeneratorAI/api_classification.py
DatasetGeneratorAI/AIComponent/__init__.py
DatasetGeneratorAI/AIComponent/src/AIModule.py
DatasetGeneratorAI/AIComponent/src/__init__.py
DatasetGeneratorAI/AIComponent/src/model.py
DatasetGeneratorAI/App/__init__.py
DatasetGeneratorAI/App/src/__init__.py
DatasetGeneratorAI/App/src/label.py
DatasetGeneratorAI/App/src/labelService.py
DatasetGeneratorAI/App/src/main.py
DatasetGeneratorAI/App/src/smartAITrainer.py
DatasetGeneratorAI/ScrapperComponent/__init__.py
DatasetGeneratorAI/ScrapperComponent/src/__init__.py
DatasetGeneratorAI/ScrapperComponent/src/scrapperModule.py
DatasetGeneratorAI-1.0.2.dist-info/LICENSE
DatasetGeneratorAI-1.0.2.dist-info/METADATA
DatasetGeneratorAI-1.0.2.dist-info/WHEEL
DatasetGeneratorAI-1.0.2.dist-info/top_level.txt
DatasetGeneratorAI-1.0.2.dist-info/RECORD
